{"assets":{"4265ED0386AC0B07B6B7753076A079BD":{"type":"texture","index":22,"assetRequest":{"type":"slide","state":"incoming","slide":"ACC38F4A-428A-4F9E-9630-C041EA9CAA2F"},"url":"assets/4265ED0386AC0B07B6B7753076A079BD.svg","width":1024,"height":768},"E34E1673E8E708C7D3CB0FFBC12ABA87":{"type":"texture","index":21,"assetRequest":{"type":"slide","state":"outgoing","slide":"612AAA78-3E95-430A-83ED-F1ADCEFE3845"},"url":"assets/E34E1673E8E708C7D3CB0FFBC12ABA87.svg","width":1024,"height":768}},"events":[{"effects":[{"beginTime":0,"baseLayer":{"animations":[],"initialState":{"affineTransform":[1,0,0,1,0,0],"masksToBounds":true,"rotation":0,"scale":1,"position":{"pointX":512,"pointY":384},"width":1024,"sublayerTransform":[1,0,0,0,0,1,0,0,0,0,1,0,0,0,0,1],"contentsRect":{"y":0,"x":0,"width":1,"height":1},"opacity":1,"edgeAntialiasingMask":0,"height":768,"hidden":false,"anchorPoint":{"pointX":0.5,"pointY":0.5}},"objectID":"0","layers":[{"animations":[],"initialState":{"affineTransform":[1,0,0,1,0,0],"masksToBounds":false,"rotation":0,"scale":1,"position":{"pointX":512,"pointY":384},"width":1024,"sublayerTransform":[1,0,0,0,0,1,0,0,0,0,1,-0.0004922987690640373,0,0,0,1],"contentsRect":{"y":0,"x":0,"width":1,"height":1},"opacity":1,"edgeAntialiasingMask":15,"height":768,"hidden":false,"anchorPoint":{"pointX":0.5,"pointY":0.5}},"layers":[{"animations":[],"layers":[],"initialState":{"affineTransform":[1,0,0,1,0,0],"masksToBounds":false,"rotation":0,"scale":1,"position":{"pointX":512,"pointY":384},"width":1024,"sublayerTransform":[1,0,0,0,0,1,0,0,0,0,1,0,0,0,0,1],"contentsRect":{"y":0,"x":0,"width":1,"height":1},"opacity":1,"edgeAntialiasingMask":0,"height":768,"hidden":false,"anchorPoint":{"pointX":0.5,"pointY":0.5}},"texture":"4265ED0386AC0B07B6B7753076A079BD"},{"animations":[{"from":{"scalar":false},"beginTime":0,"repeatCount":0,"fillMode":"both","property":"hidden","duration":0.01,"to":{"scalar":true}}],"layers":[],"initialState":{"affineTransform":[1,0,0,1,0,0],"masksToBounds":false,"rotation":0,"scale":1,"position":{"pointX":512,"pointY":384},"width":1024,"sublayerTransform":[1,0,0,0,0,1,0,0,0,0,1,0,0,0,0,1],"contentsRect":{"y":0,"x":0,"width":1,"height":1},"opacity":1,"edgeAntialiasingMask":0,"height":768,"hidden":false,"anchorPoint":{"pointX":0.5,"pointY":0.5}},"texture":"E34E1673E8E708C7D3CB0FFBC12ABA87"}]}]},"effects":[],"duration":0.01,"type":"transition","name":"none","objectID":"0"}],"automaticPlay":false,"hyperlinks":[],"accessibility":[{"text":"pasted-image.png","targetRectangle":{"y":23.62100219726562,"x":821.501220703125,"width":161.9987487792969,"height":192.7579956054688}},{"text":"Use PostGIS directly via SQL from ActiveRecord, no special gems required.","targetRectangle":{"y":214.5,"x":110.8500016429689,"width":770.1548399999999,"height":80}},{"text":"RGeo is great, but analogous to using Active Record without knowing SQL if you don’t already know PostGIS.","targetRectangle":{"y":294.5,"x":110.8500016429689,"width":813.76351875,"height":158.2205009794235}},{"text":"Plus, ActiveRecord extensions typically trail Rails development (e.g., the AR PostGIS adapter presently has problems with Rails 4.2). AR is a volatile area of the Rails codebase, so your future upgrade path may include a lot of bumps.","targetRectangle":{"y":452.7205009794235,"x":110.8500016429689,"width":819.9500399999999,"height":238.2200011014938}},{"text":"NOT Adding to Rails!","targetRectangle":{"y":73,"x":82.31263437500013,"width":737.3551999999997,"height":94}}],"baseLayer":{"animations":[],"initialState":{"affineTransform":[1,0,0,1,0,0],"masksToBounds":true,"rotation":0,"scale":1,"position":{"pointX":512,"pointY":384},"width":1024,"sublayerTransform":[1,0,0,0,0,1,0,0,0,0,1,0,0,0,0,1],"contentsRect":{"y":0,"x":0,"width":1,"height":1},"opacity":1,"edgeAntialiasingMask":0,"height":768,"hidden":false,"anchorPoint":{"pointX":0.5,"pointY":0.5}},"objectID":"0","layers":[{"animations":[],"initialState":{"affineTransform":[1,0,0,1,0,0],"masksToBounds":false,"rotation":0,"scale":1,"position":{"pointX":512,"pointY":384},"width":1024,"sublayerTransform":[1,0,0,0,0,1,0,0,0,0,1,-0.0004922987690640373,0,0,0,1],"contentsRect":{"y":0,"x":0,"width":1,"height":1},"opacity":1,"edgeAntialiasingMask":15,"height":768,"hidden":false,"anchorPoint":{"pointX":0.5,"pointY":0.5}},"layers":[{"animations":[],"layers":[],"initialState":{"affineTransform":[1,0,0,1,0,0],"masksToBounds":false,"rotation":0,"scale":1,"position":{"pointX":512,"pointY":384},"width":1024,"sublayerTransform":[1,0,0,0,0,1,0,0,0,0,1,0,0,0,0,1],"contentsRect":{"y":0,"x":0,"width":1,"height":1},"opacity":1,"edgeAntialiasingMask":0,"height":768,"hidden":false,"anchorPoint":{"pointX":0.5,"pointY":0.5}},"texture":"E34E1673E8E708C7D3CB0FFBC12ABA87"}]}]}}]}