{"assets":{"9C6244F9220D9F25C99075A71D3D32D6":{"type":"texture","index":51,"assetRequest":{"type":"slide","state":"outgoing","slide":"BB09B327-3911-4051-9927-A1DD45ED0168"},"url":"assets/9C6244F9220D9F25C99075A71D3D32D6.svg","width":1024,"height":768},"8A46F6FFCABA7F441DE8AB0DFC5C461A":{"type":"texture","index":52,"assetRequest":{"type":"slide","state":"incoming","slide":"45F1E24A-916F-487F-AF83-CE4868EB5ACC"},"url":"assets/8A46F6FFCABA7F441DE8AB0DFC5C461A.svg","width":1024,"height":768}},"events":[{"effects":[{"beginTime":0,"baseLayer":{"animations":[],"initialState":{"affineTransform":[1,0,0,1,0,0],"masksToBounds":true,"rotation":0,"scale":1,"position":{"pointX":512,"pointY":384},"width":1024,"sublayerTransform":[1,0,0,0,0,1,0,0,0,0,1,0,0,0,0,1],"contentsRect":{"y":0,"x":0,"width":1,"height":1},"opacity":1,"edgeAntialiasingMask":0,"height":768,"hidden":false,"anchorPoint":{"pointX":0.5,"pointY":0.5}},"objectID":"0","layers":[{"animations":[],"initialState":{"affineTransform":[1,0,0,1,0,0],"masksToBounds":false,"rotation":0,"scale":1,"position":{"pointX":512,"pointY":384},"width":1024,"sublayerTransform":[1,0,0,0,0,1,0,0,0,0,1,-0.0004922987690640373,0,0,0,1],"contentsRect":{"y":0,"x":0,"width":1,"height":1},"opacity":1,"edgeAntialiasingMask":15,"height":768,"hidden":false,"anchorPoint":{"pointX":0.5,"pointY":0.5}},"layers":[{"animations":[],"layers":[],"initialState":{"affineTransform":[1,0,0,1,0,0],"masksToBounds":false,"rotation":0,"scale":1,"position":{"pointX":512,"pointY":384},"width":1024,"sublayerTransform":[1,0,0,0,0,1,0,0,0,0,1,0,0,0,0,1],"contentsRect":{"y":0,"x":0,"width":1,"height":1},"opacity":1,"edgeAntialiasingMask":0,"height":768,"hidden":false,"anchorPoint":{"pointX":0.5,"pointY":0.5}},"texture":"8A46F6FFCABA7F441DE8AB0DFC5C461A"},{"animations":[{"from":{"scalar":false},"beginTime":0,"repeatCount":0,"fillMode":"both","property":"hidden","duration":0.01,"to":{"scalar":true}}],"layers":[],"initialState":{"affineTransform":[1,0,0,1,0,0],"masksToBounds":false,"rotation":0,"scale":1,"position":{"pointX":512,"pointY":384},"width":1024,"sublayerTransform":[1,0,0,0,0,1,0,0,0,0,1,0,0,0,0,1],"contentsRect":{"y":0,"x":0,"width":1,"height":1},"opacity":1,"edgeAntialiasingMask":0,"height":768,"hidden":false,"anchorPoint":{"pointX":0.5,"pointY":0.5}},"texture":"9C6244F9220D9F25C99075A71D3D32D6"}]}]},"effects":[],"duration":0.01,"type":"transition","name":"none","objectID":"0"}],"automaticPlay":false,"hyperlinks":[],"accessibility":[{"text":"irb(main):022:0> Tweet.count","targetRectangle":{"y":231.9112633958773,"x":23.83886907844695,"width":337.1484375,"height":24}},{"text":"   (52.0ms)  SELECT COUNT(*) FROM \"tweets\"","targetRectangle":{"y":255.9112633958773,"x":23.83886907844695,"width":505.7226562499999,"height":24}},{"text":"=> 340528","targetRectangle":{"y":279.9112633958773,"x":23.83886907844695,"width":108.369140625,"height":24}},{"text":"irb(main):023:0> Tweet.nearby(lat: 39, lng: -84, count: 5).map(&:distance)","targetRectangle":{"y":327.9112633958773,"x":23.83886907844695,"width":891.03515625,"height":24}},{"text":"  Tweet Load (2.0ms)        SELECT *,","targetRectangle":{"y":351.9112633958773,"x":23.83886907844695,"width":445.517578125,"height":24}},{"text":"        geom <-> ST_GeomFromEWKT('SRID=3857;POINT (-84 39)') as distance","targetRectangle":{"y":375.9112633958773,"x":23.83886907844695,"width":866.953125,"height":24}},{"text":"      FROM tweets","targetRectangle":{"y":399.9112633958773,"x":23.83886907844695,"width":204.697265625,"height":24}},{"text":"      ORDER BY distance","targetRectangle":{"y":423.9112633958773,"x":23.83886907844695,"width":276.943359375,"height":24}},{"text":"      LIMIT 5;","targetRectangle":{"y":447.9112633958773,"x":23.83886907844695,"width":168.57421875,"height":24}},{"text":"=> [0.0698045989795416, 0.129378466238647, 0.290246518133419, 0.299941772955311, 0.30044666365637]","targetRectangle":{"y":495.9112633958773,"x":23.83886907844695,"width":975.322265625,"height":48}},{"text":"Woot!","targetRectangle":{"y":598.8225325469595,"x":465.3080025674814,"width":93.38400000000001,"height":43}},{"text":"Now, we can use it in our app!","targetRectangle":{"y":40,"x":136.6207999999999,"width":769.4400000000002,"height":160}}],"baseLayer":{"animations":[],"initialState":{"affineTransform":[1,0,0,1,0,0],"masksToBounds":true,"rotation":0,"scale":1,"position":{"pointX":512,"pointY":384},"width":1024,"sublayerTransform":[1,0,0,0,0,1,0,0,0,0,1,0,0,0,0,1],"contentsRect":{"y":0,"x":0,"width":1,"height":1},"opacity":1,"edgeAntialiasingMask":0,"height":768,"hidden":false,"anchorPoint":{"pointX":0.5,"pointY":0.5}},"objectID":"0","layers":[{"animations":[],"initialState":{"affineTransform":[1,0,0,1,0,0],"masksToBounds":false,"rotation":0,"scale":1,"position":{"pointX":512,"pointY":384},"width":1024,"sublayerTransform":[1,0,0,0,0,1,0,0,0,0,1,-0.0004922987690640373,0,0,0,1],"contentsRect":{"y":0,"x":0,"width":1,"height":1},"opacity":1,"edgeAntialiasingMask":15,"height":768,"hidden":false,"anchorPoint":{"pointX":0.5,"pointY":0.5}},"layers":[{"animations":[],"layers":[],"initialState":{"affineTransform":[1,0,0,1,0,0],"masksToBounds":false,"rotation":0,"scale":1,"position":{"pointX":512,"pointY":384},"width":1024,"sublayerTransform":[1,0,0,0,0,1,0,0,0,0,1,0,0,0,0,1],"contentsRect":{"y":0,"x":0,"width":1,"height":1},"opacity":1,"edgeAntialiasingMask":0,"height":768,"hidden":false,"anchorPoint":{"pointX":0.5,"pointY":0.5}},"texture":"9C6244F9220D9F25C99075A71D3D32D6"}]}]}}]}